README.md
setup.cfg
setup.py
monocle/__init__.py
monocle/callback.py
monocle/core.py
monocle/experimental.py
monocle/monocle_mock.py
monocle/repl.py
monocle/script_util.py
monocle/util.py
monocle.egg-info/PKG-INFO
monocle.egg-info/SOURCES.txt
monocle.egg-info/dependency_links.txt
monocle.egg-info/top_level.txt
monocle/asyncore_stack/__init__.py
monocle/asyncore_stack/eventloop.py
monocle/asyncore_stack/network/__init__.py
monocle/stack/__init__.py
monocle/stack/eventloop.py
monocle/stack/network/__init__.py
monocle/stack/network/http.py
monocle/tornado_stack/__init__.py
monocle/tornado_stack/eventloop.py
monocle/tornado_stack/network/__init__.py
monocle/tornado_stack/network/http.py
monocle/twisted_stack/__init__.py
monocle/twisted_stack/eventloop.py
monocle/twisted_stack/multiprocess.py
monocle/twisted_stack/utils.py
monocle/twisted_stack/network/__init__.py
monocle/twisted_stack/network/http.py