Metadata-Version: 1.0
Name: monocle
Version: 0.40
Summary: An async programming framework with a blocking look-alike syntax
Home-page: http://github.com/saucelabs/monocle
Author: Steven Hazel
Author-email: sah@awesame.org
License: MIT
Platform: UNKNOWN
